{
 "name": "meteor",
 "label": "Meteor",  
 "homepage": "https://www.meteor.com/",
 "author": "Slava Kim <slava@meteor.com>",
 "description": "Add Meteor support. Meteor is an open-source platform for building top-quality web apps in a fraction of the time, whether you're an expert developer or just getting started.",
 "dependencies": [
  "ecma5",
  "browser"
 ],
 "repository": {
  "type": "git",
  "url": "https://github.com/Slava/tern-meteor.git"
 },
 "bugs": {
  "url": "https://github.com/Slava/tern-meteor/issues"
 },
 "help": {
  "url": "https://github.com/angelozerr/tern.java/wiki/Tern-&-Meteor-support"
 }
}